mindtrace/models/__init__.py
mindtrace_models-0.8.0.dist-info/licenses/LICENSE
mindtrace_models-0.8.0.dist-info/METADATA
mindtrace_models-0.8.0.dist-info/WHEEL
mindtrace_models-0.8.0.dist-info/top_level.txt
mindtrace_models-0.8.0.dist-info/RECORD
