Metadata-Version: 2.4
Name: mindtrace-models
Version: 0.8.0
Summary: Models for Mindtrace
Author: Mindtrace Team
License-Expression: Apache-2.0
Project-URL: Homepage, https://mindtrace.ai
Project-URL: Repository, https://github.com/mindtrace/mindtrace/blob/main/mindtrace/models
Classifier: Programming Language :: Python :: 3
Classifier: Programming Language :: Python :: 3.12
License-File: LICENSE
Requires-Dist: dill>=0.4.0
Requires-Dist: mindtrace-core>=0.8.0
Requires-Dist: mindtrace-registry>=0.8.0
Requires-Dist: mindtrace-services>=0.8.0
Requires-Dist: numpy>=2.3.1
Requires-Dist: opencv-python>=4.11.0.86
Requires-Dist: supervision>=0.26.0
Requires-Dist: torchvision>=0.22.1
Requires-Dist: ultralytics>=8.3.168
Dynamic: license-file
